x_make_pypi_x/__init__.py
x_make_pypi_x/x_cls_make_pypi_x.py
x_make_pypi_x-12.0.1.dist-info/METADATA
x_make_pypi_x-12.0.1.dist-info/WHEEL
x_make_pypi_x-12.0.1.dist-info/top_level.txt
x_make_pypi_x-12.0.1.dist-info/RECORD
